bankometer/__init__.py
bankometer/__main__.py
bankometer/config.py
bankometer/objdiff.py
bankometer/bank_modules/__init__.py
bankometer/bank_modules/yettel.py
bankometer/gnucash/__init__.py
env/bin/activate_this.py
scripts/detect_function_calls.py
bankometer-1.0.dist-info/METADATA
bankometer-1.0.dist-info/WHEEL
bankometer-1.0.dist-info/entry_points.txt
bankometer-1.0.dist-info/top_level.txt
bankometer-1.0.dist-info/RECORD
