Metadata-Version: 2.4
Name: bankometer
Version: 1.0
Summary: A command-line tool for managing bank transactions with support for multiple banks and filters.
Home-page: https://github.com/fantastic001/bankometer
Author: Stefan Nožinić
Author-email: Stefan Nožinić <stefan@lugons.org>
License-Expression: MIT
Classifier: Programming Language :: Python :: 3
Classifier: Operating System :: OS Independent
Requires-Python: >=3.6
Requires-Dist: piecash
Requires-Dist: requests
Requires-Dist: pandas
Requires-Dist: setuptools
Requires-Dist: orgasm-package
Requires-Dist: lxml
Requires-Dist: tabulate
Requires-Dist: sqlalchemy
Dynamic: author
Dynamic: home-page
Dynamic: requires-python
